audit_tools/__init__.py
audit_tools/apps.py
django_audit_tools-0.4.0.dist-info/DESCRIPTION.rst
django_audit_tools-0.4.0.dist-info/METADATA
django_audit_tools-0.4.0.dist-info/RECORD
django_audit_tools-0.4.0.dist-info/WHEEL
django_audit_tools-0.4.0.dist-info/metadata.json
django_audit_tools-0.4.0.dist-info/top_level.txt
