Metadata-Version: 2.0
Name: django-audit-tools
Version: 0.4.0
Summary: Django application that provides a set of tools for auditing requests and models and improve logging
Home-page: https://github.com/PeRDy/django-audit-tools
Author: José Antonio Perdiguero López
Author-email: perdy.hh@gmail.com
License: GNU GENERAL PUBLIC LICENSE
Requires-Dist: Django (>=1.7)
Requires-Dist: celery (>=3.1,<4.0)
Requires-Dist: django-celery (>=3.1,<4.0)
Requires-Dist: django-rest-framework-mongoengine (>=3.3,<4.0)
Requires-Dist: djangorestframework (>=3.3,<4.0)
Requires-Dist: mongoengine (>=0.8,<1.0)
Requires-Dist: psutil (>=2.1,<3.0)
